SLS/__init__.py
SLS/pipeline.py
SLS/config/__init__.py
SLS/config/colors.py
SLS/core/__init__.py
SLS/core/data_loading.py
SLS/core/deconvolution.py
SLS/core/lambda_selection.py
SLS/utils/__init__.py
SLS/utils/matrix_operations.py
SLS/utils/visualization.py
slsdeconv-0.1.1.dist-info/METADATA
slsdeconv-0.1.1.dist-info/WHEEL
slsdeconv-0.1.1.dist-info/top_level.txt
slsdeconv-0.1.1.dist-info/RECORD
