Metadata-Version: 2.4
Name: SLSDeconv
Version: 0.1.1
Summary: Fast Spatial Transcriptomics Deconvolution
Home-page: https://github.com/tinachentc/SLSDeconv
Author: Yunlu Chen
Author-email: yunluchencyl@gmail.com
Classifier: Programming Language :: Python :: 3
Classifier: License :: OSI Approved :: MIT License
Classifier: Operating System :: OS Independent
Requires-Python: >=3.11
Requires-Dist: scanpy
Requires-Dist: pandas
Requires-Dist: numpy
Requires-Dist: scipy
Requires-Dist: matplotlib
Dynamic: author
Dynamic: author-email
Dynamic: classifier
Dynamic: description
Dynamic: description-content-type
Dynamic: home-page
Dynamic: requires-dist
Dynamic: requires-python
Dynamic: summary
